{
    "namefile": [
        "Клуб 4l"
    ],
    "name_all": [
        "Клуб",
        "Клуб 4L",
        "Клуб 4К",
        "Клуб GTS"
    ],
    "name": [
        "Клуб 4L"
    ],
    "unique_name": [
        "Клуб 4L"
    ],
    "vid": [
        "стул"
    ],
    "category": [
        "стул"
    ],
    "destiny": [
        "работы и кратковременного отдыха сидя<br>Устанавливается в жилых и административных помещениях"
    ],
    "technical_requirements": [
        [
            "Стул должен соответствовать требованиям:",
            "ГОСТ 19917-2014 «Мебель для сидения и лежания. Общие технические условия»",
            "ГОСТ 26800.3-86 «Мебель для административных помещений. Функциональные размеры»",
            "настоящего технического описания",
            "комплекта конструкторской документации",
            "образцу-эталону, утвержденному в установленном порядке производителем"
        ]
    ],
    "construction_and_materials": [
        {
            "upholstery_materials": [
                "- тип покрытия каркаса стула: CH (хромовое блестящее), BL (окрашенный, цвет черный)<br>\n- материал облицовки вставки спинки и сиденья стула: кожзаменитель (Z), экокожа (S,R)<br>\n- цвет материала - по каталогу"
            ],
            "components": [
                "металлического каркаса, спинки-сиденья, пластиковых заглушек и крепежных элементов",
                "<strong>Каркас</strong> стула сварной металлический с защитно-декоративным покрытием",
                "<strong>Ножки</strong> изготовлены из стальной трубы круглого сечения Ф18х1,5 мм. Пластины из стального листа 30х30х1,5 мм<br>",
                "<strong>Покрытие каркаса:</strong> термореактивная порошковая краска черного цвета или хромовое блестящее",
                "На опорную поверхность ножек каркаса устанавливаются заглушки",
                "<strong>Спинка-сиденье</strong>, толщиной 12 мм, состоит из фанерного основания с ламинированием hpl-пластиком и покрытого бесцветным лаком. В нижней части спинки имеется эргономичный прогиб. В верхней части спинки расположено овальное отверстие под руку. Цвет спинки-сиденья: текстура светлого дерева Береза",
                "<strong>Спинка-сиденье</strong> крепится к полозьям с помощью 4-х винтов М8",
                "<strong>Сиденье</strong> обито мягким элементом (пенополиуретан) и облицовкой",
                "<strong>Материал</strong> облицовки сиденья: кожзаменитель (Z), экокожа (S,R)"
            ]
        }
    ],
    "transportation": [
        {
            "standard": "ГОСТ 16371-2014",
            "packaging": {
                "type": "5-слойный гофрокороб",
                "size": {
                    "width": 610,
                    "depth": 500,
                    "height": 510
                },
                "box_size": "610х500х510",
                "transportation": "удобства транспортировки и хранения стул поставляется в разобранном виде<br>Упаковка верхних частей по 4 шт. в отдельный L-образный гофрокороб размером <strong>570х490х170х440 мм</strong><br>Каркасы на поддон по 100 шт., оборачиваются стрейч-пленкой<br>ВОХ2 - по 2 стула в отдельный 5-слойный гофрокороб размером"
            }
        }
    ],
    "dimensions": [
        {
            "brutto": "13,7",
            "netto": "",
            "volume": "0,12"
        }
    ],
    "guarantee": [
        {
            "period": "12",
            "max_load": "120",
            "recommended_load": "90"
        }
    ],
    "images": [
        {
            "vid_main": "img/chair_visitors/klub_4l_01.png",
            "chair_view": "img/chair_visitors/klub_4l_02.png",
            "dimensions": "img/chair_visitors/dimensions/Клуб_ch4l.png",
            "box": "img/box_UTFC_2x.png"
        }
    ],
    "dimensions_details": [
        {
            "chair_height": {
                "min": 830,
                "max": 830
            },
            "headrest_height": {
                "min": null,
                "max": null
            },
            "seat_to_floor_height": {
                "min": null,
                "max": 475
            },
            "armrest_height_from_seat": {
                "min": "",
                "max": ""
            },
            "chair_depth": {
                "min": null,
                "max": 550
            },
            "seat_depth": {
                "min": null,
                "max": 410
            },
            "backrest_height": {
                "max": null,
                "min": ""
            },
            "backrest_to_seat_height": {
                "min": "",
                "max": 400
            },
            "seat_width_with_armrests": {
                "min": null,
                "max": null
            },
            "seat_width": {
                "max": 375,
                "min": ""
            },
            "diameter_cross": {
                "max": null,
                "min": ""
            },
            "runners_width": {
                "max": 505,
                "min": ""
            },
            "runners_depth": {
                "max": null,
                "min": ""
            }
        }
    ],
    "lost": [
        {
            "clean": false,
            "limit": false,
            "del":true
        }
    ]
}